configuration/__init__.py
configuration/config.py
tests/__init__.py
tests/conftest.py
tests/test_db.py
dsginfra-0.0.0.9000.dist-info/LICENCE
dsginfra-0.0.0.9000.dist-info/METADATA
dsginfra-0.0.0.9000.dist-info/WHEEL
dsginfra-0.0.0.9000.dist-info/top_level.txt
dsginfra-0.0.0.9000.dist-info/RECORD
