Metadata-Version: 2.1
Name: dsginfra
Version: 0.0.0.9000
Summary: DSG common infrastructure libraries
Home-page: https://github.com/datascienceisrael/infrastructure
Author: Data Science Group
Author-email: or@datascience.co.il, shaul@datascience.co.il, pavels@datascience.co.il
License: UNKNOWN
Platform: UNKNOWN
Classifier: License :: OSI Approved :: MIT License
Classifier: Programming Language :: Python :: 3
Classifier: Programming Language :: Python :: 3.6
Classifier: Operating System :: OS Independent
